README.md
setup.cfg
setup.py
distri5kfdsnkdsa/Binomialdistribution.py
distri5kfdsnkdsa/Gaussiandistribution.py
distri5kfdsnkdsa/Generaldistribution.py
distri5kfdsnkdsa/__init__.py
distri5kfdsnkdsa.egg-info/PKG-INFO
distri5kfdsnkdsa.egg-info/SOURCES.txt
distri5kfdsnkdsa.egg-info/dependency_links.txt
distri5kfdsnkdsa.egg-info/not-zip-safe
distri5kfdsnkdsa.egg-info/top_level.txt