Metadata-Version: 1.0
Name: distri5kfdsnkdsa
Version: 0.1
Summary: Gaussian distributions
Home-page: UNKNOWN
Author: hajar
Author-email: UNKNOWN
License: UNKNOWN
Platform: UNKNOWN
